lesiwka/__init__.py
lesiwka/__main__.py
lesiwka/_encode.py
lesiwka/ascii.py
lesiwka/diacritics.py
lesiwka/punctuation.py
lesiwka/utils.py
lesiwka/version.py
lesiwka/_decode/__init__.py
lesiwka/_decode/postprocess.py
lesiwka/_decode/preprocess.py
lesiwka/_decode/rule_1_1.py
lesiwka/_decode/rule_1_2.py
lesiwka/_decode/rule_1_3.py
lesiwka/_decode/rule_1_4.py
lesiwka/_decode/rule_1_5.py
lesiwka/_decode/rule_1_6.py
lesiwka/_decode/rule_1_7.py
lesiwka/_decode/rule_2_2.py
lesiwka/_decode/rule_3_1.py
lesiwka/_decode/rule_3_2.py
lesiwka/_decode/rule_3_4.py
lesiwka-2.1.20231022.0.dist-info/LICENSE
lesiwka-2.1.20231022.0.dist-info/METADATA
lesiwka-2.1.20231022.0.dist-info/WHEEL
lesiwka-2.1.20231022.0.dist-info/top_level.txt
lesiwka-2.1.20231022.0.dist-info/RECORD
