Metadata-Version: 2.1
Name: lesiwka
Version: 2.1.20231022.0
Summary: Python library to convert to/from Lesivka
Author: Oleksandr Tishyn
Author-email: 1079805+Mystic-Mirage@users.noreply.github.com
License: CC0 1.0 Universal
Project-URL: Source Code, https://github.com/lesiwka/python-lesiwka
Classifier: Programming Language :: Python :: 3
Classifier: Programming Language :: Python :: 3.6
Classifier: Programming Language :: Python :: 3.7
Classifier: Programming Language :: Python :: 3.8
Classifier: Programming Language :: Python :: 3.9
Classifier: Programming Language :: Python :: 3.10
Classifier: Programming Language :: Python :: 3.11
License-File: LICENSE
Provides-Extra: test
Requires-Dist: pytest ; extra == 'test'
Requires-Dist: pytest-benchmark ; extra == 'test'
